setup.py
HPPTESTPYTHONPROJECT/TCM_template.py
HPPTESTPYTHONPROJECT/TCM_template_new.py
HPPTESTPYTHONPROJECT/__init__.py
HPPTESTPYTHONPROJECT/aip_test.py
HPPTESTPYTHONPROJECT/crop_img.py
HPPTESTPYTHONPROJECT/csv2json.py
HPPTESTPYTHONPROJECT/genes.py
HPPTESTPYTHONPROJECT/get_pc.py
HPPTESTPYTHONPROJECT/html2img.py
HPPTESTPYTHONPROJECT/huankuan.py
HPPTESTPYTHONPROJECT/jy_alipay.py
HPPTESTPYTHONPROJECT/jy_alipay_requests.py
HPPTESTPYTHONPROJECT/jy_paypal.py
HPPTESTPYTHONPROJECT/kuakua.py
HPPTESTPYTHONPROJECT/pdf2img.py
HPPTESTPYTHONPROJECT/pdf_test.py
HPPTESTPYTHONPROJECT/pdf_test2.py
HPPTESTPYTHONPROJECT/rename_imgs.py
HPPTESTPYTHONPROJECT/tcm_code.py
HPPTESTPYTHONPROJECT/test.py
HPPTESTPYTHONPROJECT/test_a.py
HPPTESTPYTHONPROJECT/test_barcode.py
HPPTESTPYTHONPROJECT/test_maf.py
HPPTESTPYTHONPROJECT/test_pdf2img.py
HPPTESTPYTHONPROJECT/test_pool.py
HPPTESTPYTHONPROJECT/translate.py
HPPTESTPYTHONPROJECT/vern_test.py
HPPTESTPYTHONPROJECT/xls_text.py
jy_word/File.py
jy_word/JYFlaskApp.py
jy_word/JYPAY.py
jy_word/Word.py
jy_word/__init__.py
jy_word/demo_xml.py
jy_word/pdf2img.py
jy_word/web_tool.py
jy_word.egg-info/PKG-INFO
jy_word.egg-info/SOURCES.txt
jy_word.egg-info/dependency_links.txt
jy_word.egg-info/requires.txt
jy_word.egg-info/top_level.txt