Metadata-Version: 1.0
Name: jy-word
Version: 1.61
Summary: generate word
Home-page: https://github.com/hp910219/jy-word.git
Author: hp910219
Author-email: hp910219@126.com
License: MIT License
Keywords: word,test
Platform: UNKNOWN
